CHANGES.txt
LICENSE.txt
MANIFEST.in
README.txt
setup.py
js/__init__.py
js.galleriffic.egg-info/PKG-INFO
js.galleriffic.egg-info/SOURCES.txt
js.galleriffic.egg-info/dependency_links.txt
js.galleriffic.egg-info/entry_points.txt
js.galleriffic.egg-info/namespace_packages.txt
js.galleriffic.egg-info/not-zip-safe
js.galleriffic.egg-info/requires.txt
js.galleriffic.egg-info/top_level.txt
js/galleriffic/__init__.py
js/galleriffic/test_galleriffic.txt
js/galleriffic/resources/README.txt
js/galleriffic/resources/jquery.galleriffic.js