Metadata-Version: 1.0
Name: js.galleriffic
Version: 2.0.1-1
Summary: Fanstatic packaging of Galleriffic
Home-page: UNKNOWN
Author: Fanstatic Developers
Author-email: fanstatic@googlegroups.com
License: BSD
Keywords: Fanstatic Jquery Galleriffic
Platform: UNKNOWN
